GAUnitLibrary/__about__.py
GAUnitLibrary/__init__.py
GAUnitLibrary/version.py
robotframework_gaunitlibrary-0.0.2.dist-info/LICENSE
robotframework_gaunitlibrary-0.0.2.dist-info/METADATA
robotframework_gaunitlibrary-0.0.2.dist-info/WHEEL
robotframework_gaunitlibrary-0.0.2.dist-info/top_level.txt
robotframework_gaunitlibrary-0.0.2.dist-info/RECORD
