Metadata-Version: 2.1
Name: robotframework-gaunitlibrary
Version: 0.0.2
Summary: GAUnitLibrary is a Robot Framework library to interface with GAUnit
Home-page: UNKNOWN
Author: Vincent Cabanis
Author-email: touch@cabanis.fr
License: MIT
Platform: UNKNOWN
Classifier: Development Status :: 3 - Alpha
Classifier: Programming Language :: Python :: 3
Classifier: License :: OSI Approved :: MIT License
Classifier: Operating System :: OS Independent
Classifier: Topic :: Software Development :: Testing
Requires-Python: >=3.6
Requires-Dist: gaunit
Requires-Dist: robotframework
Requires-Dist: robotframework-seleniumlibrary
Requires-Dist: robotframework-browsermobproxylibrary
Requires-Dist: robotframework-requests
